cakemail_openapi/__init__.py
cakemail_openapi/api_client.py
cakemail_openapi/configuration.py
cakemail_openapi/exceptions.py
cakemail_openapi/rest.py
cakemail_openapi/api/__init__.py
cakemail_openapi/api/account_api.py
cakemail_openapi/api/action_api.py
cakemail_openapi/api/campaign_api.py
cakemail_openapi/api/campaign_blueprint_api.py
cakemail_openapi/api/contact_api.py
cakemail_openapi/api/custom_attribute_api.py
cakemail_openapi/api/dkim_api.py
cakemail_openapi/api/domain_api.py
cakemail_openapi/api/form_api.py
cakemail_openapi/api/interest_api.py
cakemail_openapi/api/links_api.py
cakemail_openapi/api/list_api.py
cakemail_openapi/api/log_api.py
cakemail_openapi/api/logo_api.py
cakemail_openapi/api/report_api.py
cakemail_openapi/api/segment_api.py
cakemail_openapi/api/sender_api.py
cakemail_openapi/api/sub_account_api.py
cakemail_openapi/api/suppressed_email_api.py
cakemail_openapi/api/system_email_api.py
cakemail_openapi/api/tags_api.py
cakemail_openapi/api/task_api.py
cakemail_openapi/api/template_api.py
cakemail_openapi/api/token_api.py
cakemail_openapi/api/transactional_email_api.py
cakemail_openapi/api/user_api.py
cakemail_openapi/api/webhook_api.py
cakemail_openapi/api/workflow_api.py
cakemail_openapi/api/workflow_blueprint_api.py
cakemail_openapi/models/__init__.py
cakemail_openapi/models/accept_list_policy_response.py
cakemail_openapi/models/account_full_response.py
cakemail_openapi/models/account_overrides.py
cakemail_openapi/models/account_owner.py
cakemail_openapi/models/account_owner_response.py
cakemail_openapi/models/account_owner_user.py
cakemail_openapi/models/account_response.py
cakemail_openapi/models/account_stat_response.py
cakemail_openapi/models/account_stats_response.py
cakemail_openapi/models/account_status.py
cakemail_openapi/models/account_summary_response.py
cakemail_openapi/models/accounts_response.py
cakemail_openapi/models/action.py
cakemail_openapi/models/action_blueprint.py
cakemail_openapi/models/action_condition.py
cakemail_openapi-1.12.14.dist-info/METADATA
cakemail_openapi-1.12.14.dist-info/WHEEL
cakemail_openapi-1.12.14.dist-info/top_level.txt
cakemail_openapi-1.12.14.dist-info/RECORD
