Metadata-Version: 2.1
Name: cakemail-openapi
Version: 1.12.14
Summary: OpenAPI generated client for Cakemail Next-gen API
Home-page: https://github.com/cakemail/cakemail-openapi-python
License: MIT
Platform: UNKNOWN
Requires-Python: >=3.6
Requires-Dist: six
Requires-Dist: urllib3
Requires-Dist: certifi
Requires-Dist: python-dateutil
